jaraf/__init__.py
jaraf/codes.py
jaraf/errors.py
jaraf/version.py
jaraf/mixin/__init__.py
jaraf/mixin/logfile.py
jaraf/mixin/runexecutable.py
jaraf-0.2.2.dist-info/LICENSE
jaraf-0.2.2.dist-info/METADATA
jaraf-0.2.2.dist-info/WHEEL
jaraf-0.2.2.dist-info/top_level.txt
jaraf-0.2.2.dist-info/zip-safe
jaraf-0.2.2.dist-info/RECORD
