Metadata-Version: 2.1
Name: jaraf
Version: 0.2.2
Summary: A python application framework
Home-page: https://github.com/edlabao/jaraf
Author: Edward Labao
Author-email: edlabao.dev@gmail.com
License: UNKNOWN
Platform: UNKNOWN
Classifier: Programming Language :: Python :: 3
Classifier: License :: OSI Approved :: MIT License
Classifier: Operating System :: OS Independent
